min2net/__init__.py
min2net/loss.py
min2net/utils.py
min2net/model/DeepConvNet.py
min2net/model/EEGNet.py
min2net/model/MIN2Net.py
min2net/model/MIN2Net_without_decoder.py
min2net/model/MIN2Net_without_triplet.py
min2net/model/SVM.py
min2net/model/SpectralSpatialCNN.py
min2net/model/__init__.py
min2net/preprocessing/FBCSP.py
min2net/preprocessing/SpectralSpatialMapping.py
min2net/preprocessing/__init__.py
min2net/preprocessing/config.py
min2net/preprocessing/BCIC2a/__init__.py
min2net/preprocessing/BCIC2a/fbcsp.py
min2net/preprocessing/BCIC2a/raw.py
min2net/preprocessing/BCIC2a/spectral_spatial.py
min2net/preprocessing/BCIC2a/time_domain.py
min2net/preprocessing/OpenBMI/__init__.py
min2net/preprocessing/OpenBMI/fbcsp.py
min2net/preprocessing/OpenBMI/raw.py
min2net/preprocessing/OpenBMI/spectral_spatial.py
min2net/preprocessing/OpenBMI/time_domain.py
min2net/preprocessing/SMR_BCI/__init__.py
min2net/preprocessing/SMR_BCI/fbcsp.py
min2net/preprocessing/SMR_BCI/raw.py
min2net/preprocessing/SMR_BCI/spectral_spatial.py
min2net/preprocessing/SMR_BCI/time_domain.py
min2net-1.0.1.dist-info/LICENSE
min2net-1.0.1.dist-info/METADATA
min2net-1.0.1.dist-info/WHEEL
min2net-1.0.1.dist-info/top_level.txt
min2net-1.0.1.dist-info/RECORD
