Metadata-Version: 2.1
Name: min2net
Version: 1.0.1
Summary: MIN2Net: End-to-End Multi-Task Learning for Subject-Independent Motor Imagery EEG Classification
Home-page: https://MIN2Net.github.io
Author: INTERFACES
Author-email: IoBT.VISTEC@gmail.com
License: Apache Software License
Download-URL: https://github.com/IoBT-VISTEC/MIN2Net/releases
Project-URL: Bug Tracker, https://github.com/IoBT-VISTEC/MIN2Net/issues
Project-URL: Documentation, https://MIN2Net.github.io
Project-URL: Source Code, https://github.com/IoBT-VISTEC/MIN2Net
Keywords: Brain-computer InterfacesBCI,Motor Imagery,MI,Multi-task Learning,Deep Metric Learning,DML,Autoencoder,AE,EEG Classifier
Platform: UNKNOWN
Classifier: Programming Language :: Python :: 3
Classifier: License :: OSI Approved :: Apache Software License
Classifier: Operating System :: OS Independent
Requires-Python: >=3.6
Requires-Dist: setuptools (>=42)
Requires-Dist: wheel (>=0.37.0)
Requires-Dist: tensorflow-addons (==0.9.1)
Requires-Dist: scikit-learn (>=0.24.1)
Requires-Dist: wget (>=3.2)
